discord_emoji/__init__.py
discord_emoji/methods.py
discord_emoji/table.py
discord_emoji-1.4.1.dist-info/LICENSE
discord_emoji-1.4.1.dist-info/METADATA
discord_emoji-1.4.1.dist-info/WHEEL
discord_emoji-1.4.1.dist-info/top_level.txt
discord_emoji-1.4.1.dist-info/RECORD
