Metadata-Version: 2.1
Name: discord-emoji
Version: 1.4.1
Summary: Converter of discord emoji and unicode emoji.
Home-page: https://github.com/sevenc-nanashi/discord-emoji
Author: sevenc_nanashi
License: UNKNOWN
Project-URL: Bug Tracker, https://github.com/sevenc-nanashi/discord-emoji/issues
Platform: UNKNOWN
Classifier: Programming Language :: Python :: 3.8
Classifier: Programming Language :: Python :: 3.9
Classifier: License :: OSI Approved :: MIT License
Classifier: Operating System :: OS Independent
License-File: LICENSE
